smqtk_indexing/__init__.py
smqtk_indexing/impls/__init__.py
smqtk_indexing/impls/hash_index/__init__.py
smqtk_indexing/impls/hash_index/linear.py
smqtk_indexing/impls/hash_index/sklearn_balltree.py
smqtk_indexing/impls/lsh_functor/__init__.py
smqtk_indexing/impls/lsh_functor/itq.py
smqtk_indexing/impls/lsh_functor/simple_rp.py
smqtk_indexing/impls/nn_index/__init__.py
smqtk_indexing/impls/nn_index/faiss.py
smqtk_indexing/impls/nn_index/flann.py
smqtk_indexing/impls/nn_index/lsh.py
smqtk_indexing/impls/nn_index/mrpt.py
smqtk_indexing/interfaces/__init__.py
smqtk_indexing/interfaces/hash_index.py
smqtk_indexing/interfaces/lsh_functor.py
smqtk_indexing/interfaces/nearest_neighbor_index.py
smqtk_indexing/py.typed
smqtk_indexing/utils/__init__.py
smqtk_indexing/utils/bits.py
smqtk_indexing/utils/iter_validation.py
smqtk_indexing/utils/metrics.py
smqtk_indexing/utils/progress_reporter.py
smqtk_indexing-0.18.0.dist-info/entry_points.txt
smqtk_indexing-0.18.0.dist-info/LICENSE.txt
smqtk_indexing-0.18.0.dist-info/WHEEL
smqtk_indexing-0.18.0.dist-info/METADATA
smqtk_indexing-0.18.0.dist-info/RECORD
