Metadata-Version: 2.1
Name: smqtk-indexing
Version: 0.18.0
Summary: Algorithms, data structures and utilities around computingdescriptor k-nearest-neighbors.
Home-page: https://github.com/Kitware/SMQTK-Indexing
License: BSD-3-Clause
Author: Kitware, Inc.
Author-email: smqtk-developers@kitware.com
Requires-Python: >=3.6,<4.0
Classifier: Development Status :: 3 - Alpha
Classifier: Intended Audience :: Developers
Classifier: Intended Audience :: Science/Research
Classifier: License :: OSI Approved :: BSD License
Classifier: Operating System :: MacOS :: MacOS X
Classifier: Operating System :: Unix
Classifier: Programming Language :: Python :: 3
Classifier: Programming Language :: Python :: 3.6
Classifier: Programming Language :: Python :: 3.7
Classifier: Programming Language :: Python :: 3.8
Classifier: Programming Language :: Python :: 3.9
Provides-Extra: faiss
Provides-Extra: sklearn
Requires-Dist: dataclasses (>=0.8,<0.9); python_version < "3.7"
Requires-Dist: faiss-cpu (>=1.7.0,<2.0.0); extra == "faiss"
Requires-Dist: numpy (>=1.19.5,<2.0.0)
Requires-Dist: scikit-learn (>=0.24.1,<0.25.0); extra == "sklearn"
Requires-Dist: scipy (>=1.5.2,<2.0.0)
Requires-Dist: smqtk-core (>=0.18.0)
Requires-Dist: smqtk-dataprovider (>=0.16.0)
Requires-Dist: smqtk-descriptors (>=0.18.0)
Project-URL: Documentation, https://smqtk-indexing.readthedocs.io/
Project-URL: Repository, https://github.com/Kitware/SMQTK-Indexing
